mseep_sec_edgar_mcp-0.1.3.dist-info/licenses/LICENSE
sec_edgar_mcp/config.py
sec_edgar_mcp/server.py
mseep_sec_edgar_mcp-0.1.3.dist-info/METADATA
mseep_sec_edgar_mcp-0.1.3.dist-info/WHEEL
mseep_sec_edgar_mcp-0.1.3.dist-info/top_level.txt
mseep_sec_edgar_mcp-0.1.3.dist-info/RECORD
