Metadata-Version: 2.4
Name: mseep-sec-edgar-mcp
Version: 0.1.3
Summary: SEC EDGAR MCP server for company filings and financial data
Home-page: 
Author: mseep
Author-email: mseep <support@skydeck.ai>
Maintainer-email: mseep <support@skydeck.ai>
License: MIT License
Classifier: Programming Language :: Python :: 3
Classifier: License :: OSI Approved :: MIT License
Classifier: Operating System :: OS Independent
Requires-Python: >=3.6
License-File: LICENSE
Requires-Dist: mcp[cli]>=1.7.1
Requires-Dist: secedgar==0.6.0a0
Dynamic: author
Dynamic: license-file
Dynamic: requires-python
